Metadata-Version: 1.1
Name: nominat
Version: 0.2
Summary: Case-insensitive case-preserving variable name mangler
Home-page: https://github.com/edelooff/nominat
Author: Elmer de Looff
Author-email: elmer.delooff@gmail.com
License: UNKNOWN
Keywords: name mangling anonymify
Platform: UNKNOWN
Classifier: Programming Language :: Python
